Metadata-Version: 2.1
Name: Products.FirebirdDA
Version: 0.7.1
Summary: Firebird database adapter for Zope4
Home-page: https://github.com/nakagami/Products.FirebirdDA
Author: Hajime Nakagami
Author-email: nakagami@gmail.com
License: ZPL
Keywords: Firebird
Classifier: Programming Language :: Python
Classifier: Framework :: Zope :: 4
Classifier: License :: OSI Approved :: Zope Public License
